aioemonitor/__init__.py
aioemonitor/monitor.py
aioemonitor-1.0.5.dist-info/LICENSE
aioemonitor-1.0.5.dist-info/METADATA
aioemonitor-1.0.5.dist-info/WHEEL
aioemonitor-1.0.5.dist-info/entry_points.txt
aioemonitor-1.0.5.dist-info/top_level.txt
aioemonitor-1.0.5.dist-info/RECORD
