Metadata-Version: 2.1
Name: aioemonitor
Version: 1.0.5
Summary: Asyncio Python lib for SiteSage Emonitor
Home-page: https://github.com/bdraco/aioemonitor
Author: J. Nick Koston
Author-email: nick@koston.org
License: Apache Software License 2.0
Keywords: aioemonitor
Platform: UNKNOWN
Classifier: Development Status :: 2 - Pre-Alpha
Classifier: Intended Audience :: Developers
Classifier: License :: OSI Approved :: Apache Software License
Classifier: Natural Language :: English
Classifier: Programming Language :: Python :: 3.7
Classifier: Programming Language :: Python :: 3.8
Classifier: Programming Language :: Python :: 3.9
Requires-Python: >=3.7
Provides-Extra: setup
Provides-Extra: test
Provides-Extra: dev
Provides-Extra: all
